revrseai/__init__.py
revrseai/client.py
revrseai/exceptions.py
revrseai/py.typed
revrseai/models/__init__.py
revrseai/models/endpoint.py
revrseai/models/info.py
revrseai/models/message.py
revrseai/models/response.py
revrseai/models/schema.py
revrseai/models/task.py
revrseai_python-0.1.1.dist-info/METADATA
revrseai_python-0.1.1.dist-info/WHEEL
revrseai_python-0.1.1.dist-info/licenses/LICENSE
revrseai_python-0.1.1.dist-info/RECORD
