Metadata-Version: 2.4
Name: revrseai-python
Version: 0.1.1
Summary: Python RevrseAI client library
Project-URL: Homepage, https://revrse.ai
Project-URL: Documentation, https://github.com/revrseai/revrseai-python#readme
Project-URL: Repository, https://github.com/revrseai/revrseai-python
Project-URL: Issues, https://github.com/revrseai/revrseai-python/issues
Author: RevrseAI
License: MIT
License-File: LICENSE
Keywords: android,api,automation,client,revrseai,sdk
Classifier: Development Status :: 4 - Beta
Classifier: Intended Audience :: Developers
Classifier: License :: OSI Approved :: MIT License
Classifier: Operating System :: OS Independent
Classifier: Programming Language :: Python :: 3
Classifier: Programming Language :: Python :: 3.11
Classifier: Programming Language :: Python :: 3.12
Classifier: Programming Language :: Python :: 3.13
Classifier: Topic :: Software Development :: Libraries :: Python Modules
Classifier: Typing :: Typed
Requires-Python: >=3.11
Requires-Dist: pydantic>=2.0
Requires-Dist: requests>=2.32.5
Provides-Extra: dev
Requires-Dist: mypy>=1.13; extra == 'dev'
Requires-Dist: ruff>=0.8; extra == 'dev'
Requires-Dist: types-requests>=2.32; extra == 'dev'
